gradioSearch/__init__.py
gradioSearch/__main__.py
gradioSearch/cli.py
gradioSearch/utils/__init__.py
gradioSearch/utils/compressed_faiss.py
gradioSearch/utils/gui.py
gradiosearch-0.2.3.dist-info/licenses/LICENSE
gradiosearch-0.2.3.dist-info/METADATA
gradiosearch-0.2.3.dist-info/WHEEL
gradiosearch-0.2.3.dist-info/entry_points.txt
gradiosearch-0.2.3.dist-info/top_level.txt
gradiosearch-0.2.3.dist-info/RECORD
